building_python_package/__init__.py
building_python_package/calc_kevin/__init__.py
building_python_package/calc_kevin/calc_kevin.py
project/__init__.py
project/calc.py
project/calc_kevin/__init__.py
project/calc_kevin/calc_kevin.py
calculadora_kevin-0.0.2.dist-info/METADATA
calculadora_kevin-0.0.2.dist-info/WHEEL
calculadora_kevin-0.0.2.dist-info/top_level.txt
calculadora_kevin-0.0.2.dist-info/RECORD
