Metadata-Version: 2.1
Name: calculadora-kevin
Version: 0.0.2
Summary: Projeto para bootcamp da DIO, calculadora simples
Home-page: https://github.com/Kevingtxz/Building-Python-Package
Author: Kevin Gonçalves
Author-email: kevingtxz@gmail.com
License: UNKNOWN
Platform: UNKNOWN
Requires-Python: >=3.9
